lanexpose/__init__.py
lanexpose/cli.py
lanexpose/env.py
lanexpose/webhooks.py
LANExposer-0.3.3.dist-info/METADATA
LANExposer-0.3.3.dist-info/WHEEL
LANExposer-0.3.3.dist-info/entry_points.txt
LANExposer-0.3.3.dist-info/top_level.txt
LANExposer-0.3.3.dist-info/RECORD
