Metadata-Version: 2.1
Name: LANExposer
Version: 0.3.3
Summary: Make LAN requests remotely.
Home-page: UNKNOWN
License: UNKNOWN
Platform: UNKNOWN
Requires-Dist: requests
Requires-Dist: click
Requires-Dist: flask
Requires-Dist: pyngrok
